{"chunk_definitions":[{"row":20,"row_count":1,"visible":true,"expansion_state":0,"options":{"engine":"r","include":false,"label":"unnamed-chunk-6"},"document_id":"3E8E76C5","chunk_id":"cua4jmj8ecc3m","chunk_label":"unnamed-chunk-1"},{"row":46,"row_count":1,"visible":true,"expansion_state":0,"options":{"engine":"r","include":false,"label":"unnamed-chunk-5"},"document_id":"3E8E76C5","chunk_id":"crdu07vcf9q3x","chunk_label":"unnamed-chunk-2"},{"row":173,"row_count":1,"visible":true,"expansion_state":0,"options":{"engine":"r","label":"unnamed-chunk-86"},"document_id":"3E8E76C5","chunk_id":"cwcgc99hqi27s","chunk_label":"unnamed-chunk-13"},{"row":187,"row_count":1,"visible":true,"expansion_state":0,"options":{"engine":"r","label":"unnamed-chunk-87"},"document_id":"3E8E76C5","chunk_id":"cphtxi1ghylo8","chunk_label":"unnamed-chunk-14"}],"doc_write_time":1651002900,"chunk_rendered_width":683}